.DS_Store
captool/__init__.py
captool/main.py
captool/order.py
captool2-0.1.2.dist-info/METADATA
captool2-0.1.2.dist-info/WHEEL
captool2-0.1.2.dist-info/entry_points.txt
captool2-0.1.2.dist-info/top_level.txt
captool2-0.1.2.dist-info/RECORD
