Metadata-Version: 2.1
Name: captool2
Version: 0.1.2
Summary: Core library for crawling and web scraping
Home-page: https://rescala.jp
Author: rv
Author-email: yo-maruya@rescala.jp
License: MIT
Project-URL: Bug Reports, https://github.com/rv-rescala/catsrequest/issues
Project-URL: Source, https://github.com/rv-rescala/catsrequest
Keywords: python crawler scraping
Platform: UNKNOWN
Requires-Python: >=3.7
Requires-Dist: lark-parser
Requires-Dist: catswalk2
Requires-Dist: regoogle
